codefest/cf07/hdl/synth_top.sv
// ============================================================
// compute_core.sv — Radix-2 DIF FFT Butterfly Processing Element
// Project : 256-pt FFT Vibration Anomaly Detection Accelerator
// Course  : ECE 410/510 HW4AI, Spring 2026
// Author  : Yaqoub Rabiah
//
// Description:
//   This module is the core compute kernel of the 256-point FFT
//   accelerator.  It implements one radix-2 decimation-in-frequency
//   (DIF) butterfly:
//
//       A' = A + W·B
//       B' = A − W·B
//
//   where W is the complex twiddle factor, A and B are complex
//   input samples, and A', B' are complex outputs.
//
//   Data format : INT16 / Q1.15 signed fixed-point throughout.
//   Products     : 32-bit (2×16), rescaled by arithmetic right-shift
//                  of 15 to return to Q1.15.
//   Pipeline     : 3 clock cycles latency, 1 sample/cycle throughput.
//
// Port list:
//   clk       in   1    system clock (single domain)
//   rst       in   1    synchronous active-high reset
//   valid_in  in   1    input sample valid
//   ar_in     in  16    A real  (Q1.15 signed)
//   ai_in     in  16    A imag  (Q1.15 signed)
//   br_in     in  16    B real  (Q1.15 signed)
//   bi_in     in  16    B imag  (Q1.15 signed)
//   wr_in     in  16    twiddle W real  (Q1.15 signed)
//   wi_in     in  16    twiddle W imag  (Q1.15 signed)
//   valid_out out  1    output valid (asserted 3 cycles after valid_in)
//   ar_out    out 16    A' real (Q1.15 signed)
//   ai_out    out 16    A' imag (Q1.15 signed)
//   br_out    out 16    B' real (Q1.15 signed)
//   bi_out    out 16    B' imag (Q1.15 signed)
//
// Clock domain : single clock (clk)
// Reset        : synchronous, active-high (rst)
// ============================================================

module compute_core #(
    parameter DATA_WIDTH = 16
) (
    input  logic                         clk,
    input  logic                         rst,
    // control
    input  logic                         valid_in,
    // A operand
    input  logic signed [DATA_WIDTH-1:0] ar_in,
    input  logic signed [DATA_WIDTH-1:0] ai_in,
    // B operand
    input  logic signed [DATA_WIDTH-1:0] br_in,
    input  logic signed [DATA_WIDTH-1:0] bi_in,
    // twiddle W
    input  logic signed [DATA_WIDTH-1:0] wr_in,
    input  logic signed [DATA_WIDTH-1:0] wi_in,
    // outputs
    output logic                         valid_out,
    output logic signed [DATA_WIDTH-1:0] ar_out,
    output logic signed [DATA_WIDTH-1:0] ai_out,
    output logic signed [DATA_WIDTH-1:0] br_out,
    output logic signed [DATA_WIDTH-1:0] bi_out
);

    // ------------------------------------------------------------------
    // Stage 1 — four parallel signed 16×16 multiplies
    //   W·B = (wr·br − wi·bi) + j(wr·bi + wi·br)
    // Products are 32-bit signed (Q2.30); A is pipelined alongside.
    // ------------------------------------------------------------------
    logic signed [2*DATA_WIDTH-1:0] s1_wr_br, s1_wi_bi;
    logic signed [2*DATA_WIDTH-1:0] s1_wr_bi, s1_wi_br;
    logic signed [DATA_WIDTH-1:0]   s1_ar,    s1_ai;
    logic                           s1_valid;

    always_ff @(posedge clk) begin
        if (rst) begin
            s1_wr_br <= '0;  s1_wi_bi <= '0;
            s1_wr_bi <= '0;  s1_wi_br <= '0;
            s1_ar    <= '0;  s1_ai    <= '0;
            s1_valid <= 1'b0;
        end else begin
            s1_wr_br <= wr_in * br_in;
            s1_wi_bi <= wi_in * bi_in;
            s1_wr_bi <= wr_in * bi_in;
            s1_wi_br <= wi_in * br_in;
            s1_ar    <= ar_in;
            s1_ai    <= ai_in;
            s1_valid <= valid_in;
        end
    end

    // ------------------------------------------------------------------
    // Stage 2 — combine and rescale back to Q1.15
    //   Arithmetic right-shift by (DATA_WIDTH−1 = 15) rounds Q2.30 → Q1.15
    //   Truncation to DATA_WIDTH bits takes bits [DATA_WIDTH-1:0] of result.
    //   A is pipelined again.
    // ------------------------------------------------------------------
    logic signed [DATA_WIDTH-1:0] s2_wb_r, s2_wb_i;
    logic signed [DATA_WIDTH-1:0] s2_ar,   s2_ai;
    logic                         s2_valid;

    always_ff @(posedge clk) begin
        if (rst) begin
            s2_wb_r  <= '0;  s2_wb_i  <= '0;
            s2_ar    <= '0;  s2_ai    <= '0;
            s2_valid <= 1'b0;
        end else begin
            s2_wb_r  <= (s1_wr_br - s1_wi_bi) >>> (DATA_WIDTH - 1);
            s2_wb_i  <= (s1_wr_bi + s1_wi_br) >>> (DATA_WIDTH - 1);
            s2_ar    <= s1_ar;
            s2_ai    <= s1_ai;
            s2_valid <= s1_valid;
        end
    end

    // ------------------------------------------------------------------
    // Stage 3 — butterfly add / subtract
    //   A' = A + W·B
    //   B' = A − W·B
    // ------------------------------------------------------------------
    always_ff @(posedge clk) begin
        if (rst) begin
            ar_out    <= '0;  ai_out    <= '0;
            br_out    <= '0;  bi_out    <= '0;
            valid_out <= 1'b0;
        end else begin
            ar_out    <= s2_ar + s2_wb_r;
            ai_out    <= s2_ai + s2_wb_i;
            br_out    <= s2_ar - s2_wb_r;
            bi_out    <= s2_ai - s2_wb_i;
            valid_out <= s2_valid;
        end
    end

endmodule

project/m2/tb/tb_compute_core.sv
// ============================================================
// tb_compute_core.sv — Testbench for compute_core.sv
// Course  : ECE 410/510 HW4AI, Spring 2026
//
// Reference values computed independently in Python:
//   import numpy as np
//   def q15(x): return int(round(x * 32768)) & 0xFFFF  # Q1.15 encode
//   def iq15(x): return x if x < 32768 else x - 65536   # Q1.15 decode
//
// Test vector 1  (W = 0.5 + 0j):
//   A = 100 + 0j, B = 100 + 0j, W = 0x4000 + 0j
//   W*B_r = 0x4000 * 100 >> 15 = 50
//   W*B_i = 0
//   A' = 150 + 0j   B' = 50 + 0j
//
// Test vector 2  (W = 0 + 0.5j):
//   A = 0 + 100j, B = 100 + 0j, W = 0 + 0x4000j
//   W*B_r = 0*100 - 0x4000*0   >> 15 = 0
//   W*B_i = 0*0   + 0x4000*100 >> 15 = 50
//   A' = 0 + 150j  B' = 0 + 50j
//
// Pipeline latency: 3 clock cycles.
// ============================================================
`timescale 1ns/1ps

module tb_compute_core;

    // ---- DUT signals ----
    logic        clk, rst;
    logic        valid_in, valid_out;
    logic signed [15:0] ar_in,  ai_in,  br_in,  bi_in;
    logic signed [15:0] wr_in,  wi_in;
    logic signed [15:0] ar_out, ai_out, br_out, bi_out;

    compute_core #(.DATA_WIDTH(16)) dut (
        .clk(clk), .rst(rst),
        .valid_in(valid_in),
        .ar_in(ar_in), .ai_in(ai_in),
        .br_in(br_in), .bi_in(bi_in),
        .wr_in(wr_in), .wi_in(wi_in),
        .valid_out(valid_out),
        .ar_out(ar_out), .ai_out(ai_out),
        .br_out(br_out), .bi_out(bi_out)
    );

    // ---- VCD dump for waveform viewer ----
    initial begin
        $dumpfile("compute_core.vcd");
        $dumpvars(0, tb_compute_core);
    end

    // ---- Clock: 10 ns period ----
    initial clk = 0;
    always #5 clk = ~clk;

    // ---- Pass/fail tracking ----
    integer pass_cnt = 0, fail_cnt = 0;

    task check16;
        input signed [15:0] got;
        input signed [15:0] exp;
        input [127:0]        name;
        begin
            if (got === exp) begin
                $display("  PASS  %s = %0d", name, got);
                pass_cnt = pass_cnt + 1;
            end else begin
                $display("  FAIL  %s = %0d  (expected %0d)", name, got, exp);
                fail_cnt = fail_cnt + 1;
            end
        end
    endtask

    // ---- Stimulus ----
    initial begin
        // Reset
        rst = 1; valid_in = 0;
        ar_in = 0; ai_in = 0; br_in = 0; bi_in = 0;
        wr_in = 0; wi_in = 0;
        repeat(3) @(posedge clk); #1;
        rst = 0;

        // ---- Vector 1: W = 0.5+0j, A = 100+0j, B = 100+0j ----
        // Expected: A' = 150+0j, B' = 50+0j
        @(posedge clk); #1;
        valid_in = 1;
        ar_in = 16'sd100;   ai_in = 16'sd0;
        br_in = 16'sd100;   bi_in = 16'sd0;
        wr_in = 16'h4000;   wi_in = 16'sd0;   // 0x4000 = 0.5 in Q1.15

        @(posedge clk); #1;
        valid_in = 0;

        // Pipeline latency = 3 cycles; valid_in was applied 1 cycle ago,
        // so wait 2 more rising edges to land exactly on the output cycle.
        repeat(2) @(posedge clk); #1;

        $display("--- Vector 1: W=0.5+0j, A=100+0j, B=100+0j ---");
        $display("    valid_out = %0b  (expected 1)", valid_out);
        check16(ar_out, 16'sd150, "ar_out");
        check16(ai_out, 16'sd0,   "ai_out");
        check16(br_out, 16'sd50,  "br_out");
        check16(bi_out, 16'sd0,   "bi_out");

        // ---- Vector 2: W = 0+0.5j, A = 0+100j, B = 100+0j ----
        // Expected: A' = 0+150j, B' = 0+50j
        @(posedge clk); #1;
        valid_in = 1;
        ar_in = 16'sd0;    ai_in = 16'sd100;
        br_in = 16'sd100;  bi_in = 16'sd0;
        wr_in = 16'sd0;    wi_in = 16'h4000;   // 0x4000 = 0.5 in Q1.15

        @(posedge clk); #1;
        valid_in = 0;

        repeat(2) @(posedge clk); #1;

        $display("--- Vector 2: W=0+0.5j, A=0+100j, B=100+0j ---");
        $display("    valid_out = %0b  (expected 1)", valid_out);
        check16(ar_out, 16'sd0,   "ar_out");
        check16(ai_out, 16'sd150, "ai_out");
        check16(br_out, 16'sd0,   "br_out");
        check16(bi_out, 16'sd50,  "bi_out");

        // ---- Summary ----
        $display("========================================");
        if (fail_cnt == 0)
            $display("PASS  compute_core: %0d/%0d checks passed",
                     pass_cnt, pass_cnt + fail_cnt);
        else
            $display("FAIL  compute_core: %0d failures out of %0d checks",
                     fail_cnt, pass_cnt + fail_cnt);
        $display("========================================");

        $finish;
    end

endmodule

project/m2/tb/compute_core.vcd
$date
	Sun May  3 03:32:24 2026
$end
$version
	Icarus Verilog
$end
$timescale
	1ps
$end
$scope module tb_compute_core $end
$var wire 1 ! valid_out $end
$var wire 16 " br_out [15:0] $end
$var wire 16 # bi_out [15:0] $end
$var wire 16 $ ar_out [15:0] $end
$var wire 16 % ai_out [15:0] $end
$var reg 16 & ai_in [15:0] $end
$var reg 16 ' ar_in [15:0] $end
$var reg 16 ( bi_in [15:0] $end
$var reg 16 ) br_in [15:0] $end
$var reg 1 * clk $end
$var reg 1 + rst $end
$var reg 1 , valid_in $end
$var reg 16 - wi_in [15:0] $end
$var reg 16 . wr_in [15:0] $end
$var integer 32 / fail_cnt [31:0] $end
$var integer 32 0 pass_cnt [31:0] $end
$scope module dut $end
$var wire 16 1 ai_in [15:0] $end
$var wire 16 2 ar_in [15:0] $end
$var wire 16 3 bi_in [15:0] $end
$var wire 16 4 br_in [15:0] $end
$var wire 1 * clk $end
$var wire 1 + rst $end
$var wire 1 , valid_in $end
$var wire 16 5 wi_in [15:0] $end
$var wire 16 6 wr_in [15:0] $end
$var parameter 32 7 DATA_WIDTH $end
$var reg 16 8 ai_out [15:0] $end
$var reg 16 9 ar_out [15:0] $end
$var reg 16 : bi_out [15:0] $end
$var reg 16 ; br_out [15:0] $end
$var reg 16 < s1_ai [15:0] $end
$var reg 16 = s1_ar [15:0] $end
$var reg 1 > s1_valid $end
$var reg 32 ? s1_wi_bi [31:0] $end
$var reg 32 @ s1_wi_br [31:0] $end
$var reg 32 A s1_wr_bi [31:0] $end
$var reg 32 B s1_wr_br [31:0] $end
$var reg 16 C s2_ai [15:0] $end
$var reg 16 D s2_ar [15:0] $end
$var reg 1 E s2_valid $end
$var reg 16 F s2_wb_i [15:0] $end
$var reg 16 G s2_wb_r [15:0] $end
$var reg 1 ! valid_out $end
$upscope $end
$scope task check16 $end
$var reg 16 H exp [15:0] $end
$var reg 16 I got [15:0] $end
$var reg 128 J name [127:0] $end
$upscope $end
$upscope $end
$enddefinitions $end
$comment Show the parameter values. $end
$dumpall
b10000 7
$end
#0
$dumpvars
bx J
bx I
bx H
bx G
bx F
xE
bx D
bx C
bx B
bx A
bx @
bx ?
x>
bx =
bx <
bx ;
bx :
bx 9
bx 8
b0 6
b0 5
b0 4
b0 3
b0 2
b0 1
b0 0
b0 /
b0 .
b0 -
0,
1+
0*
b0 )
b0 (
b0 '
b0 &
bx %
bx $
bx #
bx "
x!
$end
#5000
0>
b0 <
b0 =
b0 @
b0 A
b0 ?
b0 B
0E
b0 C
b0 D
b0 F
b0 G
0!
b0 #
b0 :
b0 "
b0 ;
b0 %
b0 8
b0 $
b0 9
1*
#10000
0*
#15000
1*
#20000
0*
#25000
1*
#26000
0+
#30000
0*
#35000
1*
#36000
b100000000000000 .
b100000000000000 6
b1100100 )
b1100100 4
b1100100 '
b1100100 2
1,
#40000
0*
#45000
1>
b1100100 =
b110010000000000000000 B
1*
#46000
0,
#50000
0*
#55000
1E
b1100100 D
b110010 G
0>
1*
#60000
0*
#65000
0E
1!
b110010 "
b110010 ;
b10010110 $
b10010110 9
1*
#66000
b100 0
b11000100110100101011111011011110111010101110100 J
b0 H
b0 I
#70000
0*
#75000
0!
1*
#76000
b100000000000000 -
b100000000000000 5
b0 .
b0 6
b1100100 &
b1100100 1
b0 '
b0 2
1,
#80000
0*
#85000
1>
b1100100 <
b0 =
b110010000000000000000 @
b0 B
1*
#86000
0,
#90000
0*
#95000
1E
b1100100 C
b0 D
b110010 F
b0 G
0>
1*
#100000
0*
#105000
0E
1!
b110010 #
b110010 :
b0 "
b0 ;
b10010110 %
b10010110 8
b0 $
b0 9
1*
#106000
b110010 H
b110010 I
b1000 0
b11000100110100101011111011011110111010101110100 J
