project/m2/rtl/interface.sv
// ============================================================
// interface.sv — SPI Slave Interface Module
// Project : 256-pt FFT Vibration Anomaly Detection Accelerator
// Course  : ECE 410/510 HW4AI, Spring 2026
// Author  : Yaqoub Rabiah
//
// Description:
//   SPI slave compliant with Mode 0 (CPOL=0, CPHA=0).
//   Transfers one DATA_WIDTH-bit word per transaction:
//     - Write (host→chip): CS_n falls, host clocks DATA_WIDTH bits
//       MSB-first on MOSI; rx_data and rx_valid asserted after the
//       final rising SCLK edge.
//     - Read (chip→host): tx_data must be stable before CS_n falls;
//       it is loaded into the TX shift register on CS_n falling edge
//       and shifted out MSB-first, changing on each falling SCLK edge.
//
//   SPI signals are asynchronous to clk; a 3-flop synchronizer chain
//   is used for SCLK, CS_n, and MOSI before edge detection.
//
// Transaction format (16-bit word):
//   Bits [15:8] — high byte of sample (INT16 MSB)
//   Bits  [7:0] — low byte of sample  (INT16 LSB)
//   Clock polarity : CPOL = 0 (SCLK idle LOW)
//   Clock phase    : CPHA = 0 (data captured on rising SCLK)
//
// Register / address map:
//   This module implements a single 16-bit data register.
//   Each CS transaction is one atomic read or write of that register.
//   No explicit address phase; direction determined by initiator.
//
// Port list:
//   clk       in   1    system clock (single domain, ≥10× SPI rate)
//   rst       in   1    synchronous active-high reset
//   spi_sclk  in   1    SPI serial clock from master (async)
//   spi_cs_n  in   1    SPI chip-select, active-low (async)
//   spi_mosi  in   1    master→slave data (async)
//   spi_miso  out  1    slave→master data
//   rx_data   out 16    last received word (stable after rx_valid)
//   rx_valid  out  1    pulses high 1 cycle when rx_data is new
//   tx_data   in  16    word to shift out on next read transaction
//
// Clock domain : single (clk); SPI signals synchronized via 3-FF chain
// Reset        : synchronous, active-high (rst)
// ============================================================

module spi_slave #(
    parameter DATA_WIDTH = 16
) (
    input  logic                          clk,
    input  logic                          rst,
    // SPI port (Mode 0 — CPOL=0, CPHA=0)
    input  logic                          spi_sclk,
    input  logic                          spi_cs_n,
    input  logic                          spi_mosi,
    output logic                          spi_miso,
    // Core-side data interface
    output logic [DATA_WIDTH-1:0]         rx_data,
    output logic                          rx_valid,
    input  logic [DATA_WIDTH-1:0]         tx_data
);

    // ------------------------------------------------------------------
    // 3-flop synchronizers for asynchronous SPI inputs
    // sclk_r[0] = newest capture, sclk_r[2] = oldest
    // ------------------------------------------------------------------
    logic [2:0] sclk_r, cs_r;
    logic [1:0] mosi_r;

    always_ff @(posedge clk) begin
        if (rst) begin
            sclk_r <= 3'b000;
            cs_r   <= 3'b111;   // CS_n idle high
            mosi_r <= 2'b00;
        end else begin
            sclk_r <= {sclk_r[1:0], spi_sclk};
            cs_r   <= {cs_r[1:0],   spi_cs_n};
            mosi_r <= {mosi_r[0],   spi_mosi};
        end
    end

    // ------------------------------------------------------------------
    // Edge and level detection on synchronized signals
    // ------------------------------------------------------------------
    wire sclk_posedge_det = (sclk_r[2:1] == 2'b01);
    wire sclk_negedge_det = (sclk_r[2:1] == 2'b10);
    wire cs_n_fall        = (cs_r[2:1]   == 2'b10);
    wire cs_n_active      = ~cs_r[2];          // CS_n is asserted (low)
    wire mosi_stable      = mosi_r[1];

    // ------------------------------------------------------------------
    // Shift registers and bit counter
    // ------------------------------------------------------------------
    logic [DATA_WIDTH-1:0]        rx_shift;
    logic [DATA_WIDTH-1:0]        tx_shift;
    logic [$clog2(DATA_WIDTH):0]  bit_cnt;

    always_ff @(posedge clk) begin
        if (rst) begin
            rx_shift <= '0;
            tx_shift <= '0;
            rx_data  <= '0;
            rx_valid <= 1'b0;
            bit_cnt  <= '0;
            spi_miso <= 1'b0;
        end else begin
            rx_valid <= 1'b0;               // default: deassert each cycle

            if (cs_n_fall) begin
                // Load TX register and pre-drive MSB onto MISO
                tx_shift <= tx_data;
                spi_miso <= tx_data[DATA_WIDTH-1];
                bit_cnt  <= '0;
            end else if (cs_n_active) begin
                if (sclk_posedge_det) begin
                    // Capture MOSI on rising SCLK
                    rx_shift <= {rx_shift[DATA_WIDTH-2:0], mosi_stable};
                    bit_cnt  <= bit_cnt + 1;
                    if (bit_cnt == (DATA_WIDTH - 1)) begin
                        rx_data  <= {rx_shift[DATA_WIDTH-2:0], mosi_stable};
                        rx_valid <= 1'b1;
                    end
                end
                if (sclk_negedge_det) begin
                    // Shift TX register and drive next bit on MISO
                    tx_shift <= {tx_shift[DATA_WIDTH-2:0], 1'b0};
                    spi_miso <= tx_shift[DATA_WIDTH-2];
                end
            end
        end
    end

endmodule

project/m2/tb/tb_interface.sv
// ============================================================
// tb_interface.sv — Testbench for interface.sv (SPI Slave)
// Course  : ECE 410/510 HW4AI, Spring 2026
//
// SPI Mode 0 (CPOL=0, CPHA=0):
//   - SCLK idle LOW
//   - Data captured on rising SCLK
//   - Data driven on falling SCLK (or before first rising)
//
// SPI timing in this testbench:
//   System clock  : 10 ns period (100 MHz)
//   SPI bit period: 6 system clocks (60 ns → ~16.7 MHz SPI)
//   SPI signals are driven on negedge of system clk so that
//   the 3-FF synchronizer inside the DUT meets setup time.
//
// Transactions:
//   Write test : send WRITE_WORD = 0xA5C3 on MOSI
//                verify rx_data == 0xA5C3 and rx_valid pulses
//   Read  test : pre-load TX_WORD = 0x7B2E into tx_data
//                perform a 16-clock SPI transaction
//                capture MISO bits and verify == 0x7B2E
// ============================================================
`timescale 1ns/1ps

module tb_interface;

    // ---- DUT signals ----
    logic        clk, rst;
    logic        spi_sclk, spi_cs_n, spi_mosi, spi_miso;
    logic [15:0] rx_data;
    logic        rx_valid;
    logic [15:0] tx_data;

    spi_slave #(.DATA_WIDTH(16)) dut (
        .clk(clk), .rst(rst),
        .spi_sclk(spi_sclk), .spi_cs_n(spi_cs_n),
        .spi_mosi(spi_mosi), .spi_miso(spi_miso),
        .rx_data(rx_data), .rx_valid(rx_valid),
        .tx_data(tx_data)
    );

    // ---- VCD dump ----
    initial begin
        $dumpfile("interface.vcd");
        $dumpvars(0, tb_interface);
    end

    // ---- Clock ----
    initial clk = 0;
    always #5 clk = ~clk;

    integer pass_cnt = 0, fail_cnt = 0;

    task check16;
        input [15:0] got;
        input [15:0] exp;
        input [127:0] name;
        begin
            if (got === exp) begin
                $display("  PASS  %s = 0x%04h", name, got);
                pass_cnt = pass_cnt + 1;
            end else begin
                $display("  FAIL  %s = 0x%04h  (expected 0x%04h)", name, got, exp);
                fail_cnt = fail_cnt + 1;
            end
        end
    endtask

    // ---- SPI write task ----
    // Drive 16 bits MSB-first on MOSI; CS_n active during transfer.
    task spi_write_txn;
        input [15:0] data;
        integer i;
        begin
            @(negedge clk);
            spi_cs_n = 1'b0;
            repeat(5) @(negedge clk);   // CS setup + sync latency (3 FF + margin)

            for (i = 15; i >= 0; i = i - 1) begin
                @(negedge clk);
                spi_mosi = data[i];        // set MOSI before rising SCLK
                @(negedge clk);
                spi_sclk = 1'b1;           // SCLK rises
                repeat(3) @(negedge clk);  // hold high: sync chain sees posedge
                spi_sclk = 1'b0;           // SCLK falls
                @(negedge clk);
            end

            repeat(4) @(negedge clk);
            spi_cs_n = 1'b1;             // deassert CS
            repeat(6) @(posedge clk);    // wait for rx_valid to propagate
        end
    endtask

    // ---- SPI read task ----
    // Clock out DATA_WIDTH bits; capture MISO into captured_miso.
    logic [15:0] captured_miso;
    task spi_read_txn;
        integer i;
        begin
            captured_miso = 16'h0;
            @(negedge clk);
            spi_cs_n = 1'b0;
            repeat(5) @(negedge clk);

            for (i = 15; i >= 0; i = i - 1) begin
                @(negedge clk);
                spi_mosi = 1'b0;           // don't care for read
                @(negedge clk);
                spi_sclk = 1'b1;
                repeat(3) @(negedge clk);
                captured_miso[i] = spi_miso;  // capture MISO at mid-high
                spi_sclk = 1'b0;
                @(negedge clk);
            end

            repeat(4) @(negedge clk);
            spi_cs_n = 1'b1;
            repeat(6) @(posedge clk);
        end
    endtask

    // ---- Stimulus ----
    localparam [15:0] WRITE_WORD = 16'hA5C3;
    localparam [15:0] TX_WORD    = 16'h7B2E;

    initial begin
        // Idle state
        rst      = 1; spi_sclk = 0; spi_cs_n = 1; spi_mosi = 0;
        tx_data  = TX_WORD;
        repeat(5) @(posedge clk); #1;
        rst = 0;
        repeat(3) @(posedge clk);

        // =============================================
        // Write transaction: send WRITE_WORD on MOSI
        // =============================================
        $display("--- Write transaction: sending 0x%04h ---", WRITE_WORD);
        spi_write_txn(WRITE_WORD);

        // Check rx_data captured the word
        check16(rx_data, WRITE_WORD, "rx_data");

        repeat(4) @(posedge clk);

        // =============================================
        // Read transaction: capture MISO, expect TX_WORD
        // =============================================
        $display("--- Read transaction: expecting 0x%04h on MISO ---", TX_WORD);
        spi_read_txn();

        check16(captured_miso, TX_WORD, "miso_word");

        // ---- Summary ----
        $display("========================================");
        if (fail_cnt == 0)
            $display("PASS  interface: %0d/%0d checks passed",
                     pass_cnt, pass_cnt + fail_cnt);
        else
            $display("FAIL  interface: %0d failures out of %0d checks",
                     fail_cnt, pass_cnt + fail_cnt);
        $display("========================================");

        $finish;
    end

endmodule

project/m2/tb/interface.vcd
$date
	Sun May  3 03:32:24 2026
$end
$version
	Icarus Verilog
$end
$timescale
	1ps
$end
$scope module tb_interface $end
$var wire 1 ! spi_miso $end
$var wire 1 " rx_valid $end
$var wire 16 # rx_data [15:0] $end
$var parameter 16 $ TX_WORD $end
$var parameter 16 % WRITE_WORD $end
$var reg 16 & captured_miso [15:0] $end
$var reg 1 ' clk $end
$var reg 1 ( rst $end
$var reg 1 ) spi_cs_n $end
$var reg 1 * spi_mosi $end
$var reg 1 + spi_sclk $end
$var reg 16 , tx_data [15:0] $end
$var integer 32 - fail_cnt [31:0] $end
$var integer 32 . pass_cnt [31:0] $end
$scope module dut $end
$var wire 1 ' clk $end
$var wire 1 / cs_n_active $end
$var wire 1 ( rst $end
$var wire 1 ) spi_cs_n $end
$var wire 1 * spi_mosi $end
$var wire 1 + spi_sclk $end
$var wire 16 0 tx_data [15:0] $end
$var wire 1 1 sclk_posedge_det $end
$var wire 1 2 sclk_negedge_det $end
$var wire 1 3 mosi_stable $end
$var wire 1 4 cs_n_fall $end
$var parameter 32 5 DATA_WIDTH $end
$var reg 5 6 bit_cnt [4:0] $end
$var reg 3 7 cs_r [2:0] $end
$var reg 2 8 mosi_r [1:0] $end
$var reg 16 9 rx_data [15:0] $end
$var reg 16 : rx_shift [15:0] $end
$var reg 1 " rx_valid $end
$var reg 3 ; sclk_r [2:0] $end
$var reg 1 ! spi_miso $end
$var reg 16 < tx_shift [15:0] $end
$upscope $end
$scope task check16 $end
$var reg 16 = exp [15:0] $end
$var reg 16 > got [15:0] $end
$var reg 128 ? name [127:0] $end
$upscope $end
$scope task spi_read_txn $end
$var integer 32 @ i [31:0] $end
$upscope $end
$scope task spi_write_txn $end
$var reg 16 A data [15:0] $end
$var integer 32 B i [31:0] $end
$upscope $end
$upscope $end
$enddefinitions $end
$comment Show the parameter values. $end
$dumpall
b10000 5
b1010010111000011 %
b111101100101110 $
$end
#0
$dumpvars
bx B
bx A
bx @
bx ?
bx >
bx =
bx <
bx ;
bx :
bx 9
bx 8
bx 7
bx 6
x4
x3
x2
x1
b111101100101110 0
x/
b0 .
b0 -
b111101100101110 ,
0+
0*
1)
1(
0'
bx &
bx #
x"
x!
$end
#5000
0/
03
04
01
02
b0 8
b111 7
b0 ;
0!
b0 6
0"
b0 #
b0 9
b0 <
b0 :
1'
#10000
0'
#15000
1'
#20000
0'
#25000
1'
#30000
0'
#35000
1'
#40000
0'
#45000
1'
#46000
0(
#50000
0'
#55000
1'
#60000
0'
#65000
1'
#70000
0'
#75000
b1010010111000011 A
1'
#80000
0)
0'
#85000
b110 7
1'
#90000
0'
#95000
14
b100 7
1'
#100000
0'
#105000
1/
04
b0 7
b111101100101110 <
1'
#110000
0'
#115000
1'
#120000
0'
#125000
1'
#130000
b1111 B
0'
#135000
1'
#140000
1*
0'
#145000
b1 8
1'
#150000
1+
0'
#155000
13
b11 8
b1 ;
1'
#160000
0'
#165000
11
b11 ;
1'
#170000
0'
#175000
01
b1 6
b1 :
b111 ;
1'
#180000
0+
0'
#185000
b110 ;
1'
#190000
b1110 B
0'
#195000
12
b100 ;
1'
#200000
0*
0'
#205000
02
b10 8
b0 ;
1!
b1111011001011100 <
1'
#210000
1+
0'
#215000
03
b0 8
b1 ;
1'
#220000
0'
#225000
11
b11 ;
1'
#230000
0'
#235000
01
b10 6
b10 :
b111 ;
1'
#240000
0+
0'
#245000
b110 ;
1'
#250000
b1101 B
0'
#255000
12
b100 ;
1'
#260000
1*
0'
#265000
02
b1 8
b0 ;
b1110110010111000 <
1'
#270000
1+
0'
#275000
13
b11 8
b1 ;
1'
#280000
0'
#285000
11
b11 ;
1'
#290000
0'
#295000
01
b11 6
b101 :
b111 ;
1'
#300000
0+
0'
#305000
b110 ;
1'
#310000
b1100 B
0'
#315000
12
b100 ;
1'
#320000
0*
0'
#325000
02
b10 8
b0 ;
b1101100101110000 <
1'
#330000
1+
0'
#335000
03
b0 8
b1 ;
1'
#340000
0'
#345000
11
b11 ;
1'
#350000
0'
#355000
01
b100 6
b1010 :
b111 ;
1'
#360000
0+
0'
#365000
b110 ;
1'
#370000
b1011 B
0'
#375000
12
b100 ;
1'
#380000
0'
#385000
02
b0 ;
b1011001011100000 <
1'
#390000
1+
0'
#395000
b1 ;
1'
#400000
0'
#405000
11
b11 ;
1'
#410000
0'
#415000
01
b101 6
b10100 :
b111 ;
1'
#420000
0+
0'
#425000
b110 ;
1'
#430000
b1010 B
0'
#435000
12
b100 ;
1'
#440000
1*
0'
#445000
02
b1 8
b0 ;
0!
b110010111000000 <
1'
#450000
1+
0'
#455000
13
b11 8
b1 ;
1'
#460000
0'
#465000
11
b11 ;
1'
#470000
0'
#475000
01
b110 6
b101001 :
b111 ;
1'
#480000
0+
0'
#485000
b110 ;
1'
#490000
b1001 B
0'
#495000
12
b100 ;
1'
#500000
0*
0'
#505000
02
b10 8
b0 ;
1!
b1100101110000000 <
1'
#510000
1+
0'
#515000
03
b0 8
b1 ;
1'
#520000
0'
#525000
11
b11 ;
1'
#530000
0'
#535000
01
b111 6
b1010010 :
b111 ;
1'
#540000
0+
0'
#545000
b110 ;
1'
#550000
b1000 B
0'
#555000
12
b100 ;
1'
#560000
1*
0'
#565000
02
b1 8
b0 ;
b1001011100000000 <
1'
#570000
1+
0'
#575000
13
b11 8
b1 ;
1'
#580000
0'
#585000
11
b11 ;
1'
#590000
0'
#595000
01
b1000 6
b10100101 :
b111 ;
1'
#600000
0+
0'
#605000
b110 ;
1'
#610000
b111 B
0'
#615000
12
b100 ;
1'
#620000
0'
#625000
02
b0 ;
0!
b10111000000000 <
1'
#630000
1+
0'
#635000
b1 ;
1'
#640000
0'
#645000
11
b11 ;
1'
#650000
0'
#655000
01
b1001 6
b101001011 :
b111 ;
1'
#660000
0+
0'
#665000
b110 ;
1'
#670000
b110 B
0'
#675000
12
b100 ;
1'
#680000
0'
#685000
02
b0 ;
b101110000000000 <
1'
#690000
1+
0'
#695000
b1 ;
1'
#700000
0'
#705000
11
b11 ;
1'
#710000
0'
#715000
01
b1010 6
b1010010111 :
b111 ;
1'
#720000
0+
0'
#725000
b110 ;
1'
#730000
b101 B
0'
#735000
12
b100 ;
1'
#740000
0*
0'
#745000
02
b10 8
b0 ;
1!
b1011100000000000 <
1'
#750000
1+
0'
#755000
03
b0 8
b1 ;
1'
#760000
0'
#765000
11
b11 ;
1'
#770000
0'
#775000
01
b1011 6
b10100101110 :
b111 ;
1'
#780000
0+
0'
#785000
b110 ;
1'
#790000
b100 B
0'
#795000
12
b100 ;
1'
#800000
0'
#805000
02
b0 ;
0!
b111000000000000 <
1'
#810000
1+
0'
#815000
b1 ;
1'
#820000
0'
#825000
11
b11 ;
1'
#830000
0'
#835000
01
b1100 6
b101001011100 :
b111 ;
1'
#840000
0+
0'
#845000
b110 ;
1'
#850000
b11 B
0'
#855000
12
b100 ;
1'
#860000
0'
#865000
02
b0 ;
1!
b1110000000000000 <
1'
#870000
1+
0'
#875000
b1 ;
1'
#880000
0'
#885000
11
b11 ;
1'
#890000
0'
#895000
01
b1101 6
b1010010111000 :
b111 ;
1'
#900000
0+
0'
#905000
b110 ;
1'
#910000
b10 B
0'
#915000
12
b100 ;
1'
#920000
0'
#925000
02
b0 ;
b1100000000000000 <
1'
#930000
1+
0'
#935000
b1 ;
1'
#940000
0'
#945000
11
b11 ;
1'
#950000
0'
#955000
01
b1110 6
b10100101110000 :
b111 ;
1'
#960000
0+
0'
#965000
b110 ;
1'
#970000
b1 B
0'
#975000
12
b100 ;
1'
#980000
1*
0'
#985000
02
b1 8
b0 ;
b1000000000000000 <
1'
#990000
1+
0'
#995000
13
b11 8
b1 ;
1'
#1000000
0'
#1005000
11
b11 ;
1'
#1010000
0'
#1015000
01
b1111 6
b101001011100001 :
b111 ;
1'
#1020000
0+
0'
#1025000
b110 ;
1'
#1030000
b0 B
0'
#1035000
12
b100 ;
1'
#1040000
0'
#1045000
02
b0 ;
0!
b0 <
1'
#1050000
1+
0'
#1055000
b1 ;
1'
#1060000
0'
#1065000
11
b11 ;
1'
#1070000
0'
#1075000
01
1"
b1010010111000011 #
b1010010111000011 9
b10000 6
b1010010111000011 :
b111 ;
1'
#1080000
0+
0'
#1085000
b110 ;
0"
1'
#1090000
b11111111111111111111111111111111 B
0'
#1095000
12
b100 ;
1'
#1100000
0'
#1105000
02
b0 ;
1'
#1110000
0'
#1115000
1'
#1120000
0'
#1125000
1'
#1130000
1)
0'
#1135000
b1 7
1'
#1140000
0'
#1145000
b11 7
1'
#1150000
0'
#1155000
0/
b111 7
1'
#1160000
0'
#1165000
1'
#1170000
0'
#1175000
1'
#1180000
0'
#1185000
b1 .
b1110010011110000101111101100100011000010111010001100001 ?
b1010010111000011 =
b1010010111000011 >
1'
#1190000
0'
#1195000
1'
#1200000
0'
#1205000
1'
#1210000
0'
#1215000
1'
#1220000
0'
#1225000
b0 &
1'
#1230000
0)
0'
#1235000
b110 7
1'
#1240000
0'
#1245000
14
b100 7
1'
#1250000
0'
#1255000
1/
04
b0 6
b111101100101110 <
b0 7
1'
#1260000
0'
#1265000
1'
#1270000
0'
#1275000
1'
#1280000
b1111 @
0'
#1285000
1'
#1290000
0*
0'
#1295000
b10 8
1'
#1300000
1+
0'
#1305000
03
b0 8
b1 ;
1'
#1310000
0'
#1315000
11
b11 ;
1'
#1320000
0'
#1325000
01
b111 ;
b1 6
b100101110000110 :
1'
#1330000
0+
0'
#1335000
b110 ;
1'
#1340000
b1110 @
0'
#1345000
12
b100 ;
1'
#1350000
0'
#1355000
02
1!
b1111011001011100 <
b0 ;
1'
#1360000
1+
0'
#1365000
b1 ;
1'
#1370000
0'
#1375000
11
b11 ;
1'
#1380000
0'
#1385000
01
b111 ;
b10 6
b1001011100001100 :
1'
#1390000
0+
b100000000000000 &
0'
#1395000
b110 ;
1'
#1400000
b1101 @
0'
#1405000
12
b100 ;
1'
#1410000
0'
#1415000
02
b1110110010111000 <
b0 ;
1'
#1420000
1+
0'
#1425000
b1 ;
1'
#1430000
0'
#1435000
11
b11 ;
1'
#1440000
0'
#1445000
01
b111 ;
b11 6
b10111000011000 :
1'
#1450000
0+
b110000000000000 &
0'
#1455000
b110 ;
1'
#1460000
b1100 @
0'
#1465000
12
b100 ;
1'
#1470000
0'
#1475000
02
b1101100101110000 <
b0 ;
1'
#1480000
1+
0'
#1485000
b1 ;
1'
#1490000
0'
#1495000
11
b11 ;
1'
#1500000
0'
#1505000
01
b111 ;
b100 6
b101110000110000 :
1'
#1510000
0+
b111000000000000 &
0'
#1515000
b110 ;
1'
#1520000
b1011 @
0'
#1525000
12
b100 ;
1'
#1530000
0'
#1535000
02
b1011001011100000 <
b0 ;
1'
#1540000
1+
0'
#1545000
b1 ;
1'
#1550000
0'
#1555000
11
b11 ;
1'
#1560000
0'
#1565000
01
b111 ;
b101 6
b1011100001100000 :
1'
#1570000
0+
b111100000000000 &
0'
#1575000
b110 ;
1'
#1580000
b1010 @
0'
#1585000
12
b100 ;
1'
#1590000
0'
#1595000
02
0!
b110010111000000 <
b0 ;
1'
#1600000
1+
0'
#1605000
b1 ;
1'
#1610000
0'
#1615000
11
b11 ;
1'
#1620000
0'
#1625000
01
b111 ;
b110 6
b111000011000000 :
1'
#1630000
0+
0'
#1635000
b110 ;
1'
#1640000
b1001 @
0'
#1645000
12
b100 ;
1'
#1650000
0'
#1655000
02
1!
b1100101110000000 <
b0 ;
1'
#1660000
1+
0'
#1665000
b1 ;
1'
#1670000
0'
#1675000
11
b11 ;
1'
#1680000
0'
#1685000
01
b111 ;
b111 6
b1110000110000000 :
1'
#1690000
0+
b111101000000000 &
0'
#1695000
b110 ;
1'
#1700000
b1000 @
0'
#1705000
12
b100 ;
1'
#1710000
0'
#1715000
02
b1001011100000000 <
b0 ;
1'
#1720000
1+
0'
#1725000
b1 ;
1'
#1730000
0'
#1735000
11
b11 ;
1'
#1740000
0'
#1745000
01
b111 ;
b1000 6
b1100001100000000 :
1'
#1750000
0+
b111101100000000 &
0'
#1755000
b110 ;
1'
#1760000
b111 @
0'
#1765000
12
b100 ;
1'
#1770000
0'
#1775000
02
0!
b10111000000000 <
b0 ;
1'
#1780000
1+
0'
#1785000
b1 ;
1'
#1790000
0'
#1795000
11
b11 ;
1'
#1800000
0'
#1805000
01
b111 ;
b1001 6
b1000011000000000 :
1'
#1810000
0+
0'
#1815000
b110 ;
1'
#1820000
b110 @
0'
#1825000
12
b100 ;
1'
#1830000
0'
#1835000
02
b101110000000000 <
b0 ;
1'
#1840000
1+
0'
#1845000
b1 ;
1'
#1850000
0'
#1855000
11
b11 ;
1'
#1860000
0'
#1865000
01
b111 ;
b1010 6
b110000000000 :
1'
#1870000
0+
0'
#1875000
b110 ;
1'
#1880000
b101 @
0'
#1885000
12
b100 ;
1'
#1890000
0'
#1895000
02
1!
b1011100000000000 <
b0 ;
1'
#1900000
1+
0'
#1905000
b1 ;
1'
#1910000
0'
#1915000
11
b11 ;
1'
#1920000
0'
#1925000
01
b111 ;
b1011 6
b1100000000000 :
1'
#1930000
0+
b111101100100000 &
0'
#1935000
b110 ;
1'
#1940000
b100 @
0'
#1945000
12
b100 ;
1'
#1950000
0'
#1955000
02
0!
b111000000000000 <
b0 ;
1'
#1960000
1+
0'
#1965000
b1 ;
1'
#1970000
0'
#1975000
11
b11 ;
1'
#1980000
0'
#1985000
01
b111 ;
b1100 6
b11000000000000 :
1'
#1990000
0+
0'
#1995000
b110 ;
1'
#2000000
b11 @
0'
#2005000
12
b100 ;
1'
#2010000
0'
#2015000
02
1!
b1110000000000000 <
b0 ;
1'
#2020000
1+
0'
#2025000
b1 ;
1'
#2030000
0'
#2035000
11
b11 ;
1'
#2040000
0'
#2045000
01
b111 ;
b1101 6
b110000000000000 :
1'
#2050000
0+
b111101100101000 &
0'
#2055000
b110 ;
1'
#2060000
b10 @
0'
#2065000
12
b100 ;
1'
#2070000
0'
#2075000
02
b1100000000000000 <
b0 ;
1'
#2080000
1+
0'
#2085000
b1 ;
1'
#2090000
0'
#2095000
11
b11 ;
1'
#2100000
0'
#2105000
01
b111 ;
b1110 6
b1100000000000000 :
1'
#2110000
0+
b111101100101100 &
0'
#2115000
b110 ;
1'
#2120000
b1 @
0'
#2125000
12
b100 ;
1'
#2130000
0'
#2135000
02
b1000000000000000 <
b0 ;
1'
#2140000
1+
0'
#2145000
b1 ;
1'
#2150000
0'
#2155000
11
b11 ;
1'
#2160000
0'
#2165000
01
b111 ;
b1111 6
b1000000000000000 :
1'
#2170000
0+
b111101100101110 &
0'
#2175000
b110 ;
1'
#2180000
b0 @
0'
#2185000
12
b100 ;
1'
#2190000
0'
#2195000
02
0!
b0 <
b0 ;
1'
#2200000
1+
0'
#2205000
b1 ;
1'
#2210000
0'
#2215000
11
b11 ;
1'
#2220000
0'
#2225000
01
b111 ;
1"
b0 #
b0 9
b10000 6
b0 :
1'
#2230000
0+
0'
#2235000
0"
b110 ;
1'
#2240000
b11111111111111111111111111111111 @
0'
#2245000
12
b100 ;
1'
#2250000
0'
#2255000
02
b0 ;
1'
#2260000
0'
#2265000
1'
#2270000
0'
#2275000
1'
#2280000
1)
0'
#2285000
b1 7
1'
#2290000
0'
#2295000
b11 7
1'
#2300000
0'
#2305000
0/
b111 7
1'
#2310000
0'
#2315000
1'
#2320000
0'
#2325000
1'
#2330000
0'
#2335000
b10 .
b11011010110100101110011011011110101111101110111011011110111001001100100 ?
b111101100101110 =
b111101100101110 >
1'
